py_net_diags/__init__.py
py_net_diags/cache_manager.py
py_net_diags/config_manager.py
py_net_diags/cw_api.py
py_net_diags/network_diagnostics.py
py_net_diags-0.1.6.dist-info/METADATA
py_net_diags-0.1.6.dist-info/WHEEL
py_net_diags-0.1.6.dist-info/RECORD
