Metadata-Version: 2.3
Name: py-net-diags
Version: 0.1.6
Summary: Gets various network diagnostics for a pc
License: MIT
Author: VinnyVanGogh
Author-email: 133192356+VinnyVanGogh@users.noreply.github.com
Requires-Python: >=3.12,<4.0
Classifier: License :: OSI Approved :: MIT License
Classifier: Programming Language :: Python :: 3
Classifier: Programming Language :: Python :: 3.12
Classifier: Programming Language :: Python :: 3.13
Provides-Extra: speedcheck
Requires-Dist: cw-rpa (>=1.0.1,<2.0.0)
Requires-Dist: markdown (>=3.8,<4.0)
Requires-Dist: psutil (>=7.0.0,<8.0.0)
Requires-Dist: python-dotenv (>=1.1.0,<2.0.0)
Requires-Dist: speedcheck (>=0.0.5,<0.0.6) ; extra == "speedcheck"
Requires-Dist: speedtest-cli (>=2.1.3,<3.0.0)
Requires-Dist: tenacity (>=9.1.2,<10.0.0)
Requires-Dist: xhtml2pdf (>=0.2.17,<0.3.0)
